README.md
figureAltCaption.py
setup.py
figureAltCaption.egg-info/PKG-INFO
figureAltCaption.egg-info/SOURCES.txt
figureAltCaption.egg-info/dependency_links.txt
figureAltCaption.egg-info/requires.txt
figureAltCaption.egg-info/top_level.txt