Metadata-Version: 1.0
Name: figureAltCaption
Version: 0.0.0
Summary: Extension for Python-Markdown to parse images with captions.
Home-page: https://github.com/jdittrich/figureAltCaption
Author: UNKNOWN
Author-email: UNKNOWN
License: UNKNOWN
Platform: UNKNOWN
